mocksrv/__init__.py
mocksrv/app.py
mocksrv/app/__init__.py
mocksrv/app/app.py
mocksrv/configurator/__init__.py
mocksrv/configurator/reader.py
mocksrv/handlers/__init__.py
mocksrv/handlers/cgi.py
mocksrv/handlers/proxy.py
mocksrv/handlers/static.py
mocksrv/handlers/text.py
mocksrv/router/__init__.py
mocksrv/router/resolver.py
cmdline_mocksrv-1.0.0.dist-info/LICENSE
cmdline_mocksrv-1.0.0.dist-info/METADATA
cmdline_mocksrv-1.0.0.dist-info/WHEEL
cmdline_mocksrv-1.0.0.dist-info/top_level.txt
cmdline_mocksrv-1.0.0.dist-info/RECORD
